kgx/__init__.py
kgx/cli/__init__.py
kgx/cli/cli_utils.py
kgx/config.py
kgx/config.yml
kgx/curie_lookup_service.py
kgx/error_detection.py
kgx/graph/__init__.py
kgx/graph/base_graph.py
kgx/graph/nx_graph.py
kgx/graph_operations/__init__.py
kgx/graph_operations/clique_merge.py
kgx/graph_operations/graph_merge.py
kgx/graph_operations/meta_knowledge_graph.py
kgx/graph_operations/summarize_graph.py
kgx/parsers/__init__.py
kgx/parsers/ntriples_parser.py
kgx/prefix_manager.py
kgx/schema/__init__.py
kgx/schema/kgx.yaml
kgx/schema/kgx_complete.yaml
kgx/schema/kgx_merged.yaml
kgx/schema/scripts/__init__.py
kgx/schema/scripts/generate_transform.py
kgx/schema/scripts/rebuild_schema.py
kgx/schema/transformations/biolink_to_kgx.transform.yaml
kgx/schema/transformations/kgx_inheritance.transform.yaml
kgx/sink/__init__.py
kgx/sink/graph_sink.py
kgx/sink/json_sink.py
kgx/sink/jsonl_sink.py
kgx/sink/neo_sink.py
kgx/sink/null_sink.py
kgx/sink/parquet_sink.py
kgx/sink/rdf_sink.py
kgx/sink/sink.py
kgx/sink/sql_sink.py
kgx/sink/trapi_sink.py
kgx/sink/tsv_sink.py
kgx/source/__init__.py
kgx/source/duckdb_source.py
kgx/source/graph_source.py
kgx/source/json_source.py
kgx/source/jsonl_source.py
kgx/source/neo_source.py
kgx/source/obograph_source.py
kgx/source/owl_source.py
kgx/source/rdf_source.py
kgx/source/source.py
kgx/source/sssom_source.py
kgx/source/trapi_source.py
kgx/source/tsv_source.py
kgx/transformer.py
kgx/utils/__init__.py
kgx/utils/graph_utils.py
kgx/utils/infores.py
kgx/utils/kgx_utils.py
kgx/utils/rdf_utils.py
kgx/validator.py
kgx-2.6.0.dist-info/LICENSE
kgx-2.6.0.dist-info/METADATA
kgx-2.6.0.dist-info/WHEEL
kgx-2.6.0.dist-info/entry_points.txt
kgx-2.6.0.dist-info/RECORD
