Metadata-Version: 2.3
Name: kgx
Version: 2.6.0
Summary: A Python library and set of command line utilities for exchanging Knowledge Graphs (KGs) that conform to or are aligned to the Biolink Model.
License: BSD
Author: Deepak Unni
Author-email: deepak.unni3@gmail.com
Requires-Python: >=3.9,<4.0
Classifier: Intended Audience :: Science/Research
Classifier: License :: OSI Approved :: BSD License
Classifier: License :: Other/Proprietary License
Classifier: Programming Language :: Python :: 3
Classifier: Programming Language :: Python :: 3.9
Classifier: Programming Language :: Python :: 3.10
Classifier: Programming Language :: Python :: 3.11
Classifier: Programming Language :: Python :: 3.12
Classifier: Programming Language :: Python :: 3.13
Classifier: Topic :: Scientific/Engineering :: Bio-Informatics
Requires-Dist: Click
Requires-Dist: SPARQLWrapper (>=1.8.2)
Requires-Dist: bmt (>=1.4.0,<2.0.0)
Requires-Dist: cachetools (>=5.0.0,<6.0.0)
Requires-Dist: deprecation (>=2.1.0,<3.0.0)
Requires-Dist: docker (>=6.0.0,<7.0.0)
Requires-Dist: docutils (>=0.18.1)
Requires-Dist: duckdb (>=1.0.0,<2.0.0)
Requires-Dist: ijson (>=3.1.3,<4.0.0)
Requires-Dist: inflection (>=0.5.1,<0.6.0)
Requires-Dist: jsonlines (>=4.0.0,<5.0.0)
Requires-Dist: jsonstreams (>=0.6.0,<0.7.0)
Requires-Dist: linkml (>=1.9.1,<2.0.0)
Requires-Dist: linkml-map (>=0.3.8,<0.4.0)
Requires-Dist: linkml-runtime (>=1.9.1,<2.0.0)
Requires-Dist: mypy
Requires-Dist: neo4j (>=4.4.10)
Requires-Dist: networkx
Requires-Dist: ordered-set (>=4.0.2,<5.0.0)
Requires-Dist: pandas (>1.0.3)
Requires-Dist: prefixcommons (>=0.1.4,<0.2.0)
Requires-Dist: prologterms (>=0.0.6,<0.0.7)
Requires-Dist: pyarrow (>=15.0.2,<16.0.0)
Requires-Dist: pytest
Requires-Dist: python-dateutil (>=2.8.1,<3.0.0)
Requires-Dist: pyyaml
Requires-Dist: rdflib (>=6.0.0)
Requires-Dist: recommonmark (==0.5.0)
Requires-Dist: shexjsg
Requires-Dist: sphinx (==5.3.0)
Requires-Dist: stringcase (>=1.2.0,<2.0.0)
Requires-Dist: terminaltables (>=3.1.0,<4.0.0)
Requires-Dist: tox (>=4.13.0,<5.0.0)
Requires-Dist: validators (>=0.20.0,<0.21.0)
